langgraph_api/__init__.py
langgraph_api/asgi_transport.py
langgraph_api/asyncio.py
langgraph_api/cli.py
langgraph_api/command.py
langgraph_api/cron_scheduler.py
langgraph_api/errors.py
langgraph_api/executor_entrypoint.py
langgraph_api/feature_flags.py
langgraph_api/graph.py
langgraph_api/http.py
langgraph_api/http_metrics.py
langgraph_api/http_metrics_utils.py
langgraph_api/logging.py
langgraph_api/metadata.py
langgraph_api/patch.py
langgraph_api/queue_entrypoint.py
langgraph_api/route.py
langgraph_api/schema.py
langgraph_api/self_hosted_logs.py
langgraph_api/self_hosted_metrics.py
langgraph_api/serde.py
langgraph_api/server.py
langgraph_api/sse.py
langgraph_api/state.py
langgraph_api/store.py
langgraph_api/stream.py
langgraph_api/thread_ttl.py
langgraph_api/traceblock.py
langgraph_api/validation.py
langgraph_api/webhook.py
langgraph_api/worker.py
langgraph_api/api/__init__.py
langgraph_api/api/a2a.py
langgraph_api/api/assistants.py
langgraph_api/api/encryption_middleware.py
langgraph_api/api/mcp.py
langgraph_api/api/meta.py
langgraph_api/api/openapi.py
langgraph_api/api/profile.py
langgraph_api/api/runs.py
langgraph_api/api/store.py
langgraph_api/api/threads.py
langgraph_api/api/ui.py
langgraph_api/auth/__init__.py
langgraph_api/auth/custom.py
langgraph_api/auth/middleware.py
langgraph_api/auth/noop.py
langgraph_api/auth/studio_user.py
langgraph_api/auth/langsmith/__init__.py
langgraph_api/auth/langsmith/backend.py
langgraph_api/auth/langsmith/client.py
langgraph_api/config/__init__.py
langgraph_api/config/_parse.py
langgraph_api/config/schemas.py
langgraph_api/encryption/__init__.py
langgraph_api/encryption/context.py
langgraph_api/encryption/custom.py
langgraph_api/grpc/__init__.py
langgraph_api/grpc/client.py
langgraph_api/grpc/config_conversion.py
langgraph_api/grpc/generated/__init__.py
langgraph_api/grpc/generated/core_api_pb2.py
langgraph_api/grpc/generated/core_api_pb2.pyi
langgraph_api/grpc/generated/core_api_pb2_grpc.py
langgraph_api-0.6.16.dist-info/METADATA
langgraph_api-0.6.16.dist-info/WHEEL
langgraph_api-0.6.16.dist-info/entry_points.txt
langgraph_api-0.6.16.dist-info/licenses/LICENSE
langgraph_api-0.6.16.dist-info/RECORD
