Metadata-Version: 2.4
Name: langgraph-api
Version: 0.6.16
Author-email: Will Fu-Hinthorn <will@langchain.dev>, Josh Rogers <josh@langchain.dev>, Parker Rule <parker@langchain.dev>
License: Elastic-2.0
License-File: LICENSE
Requires-Python: >=3.11
Requires-Dist: cloudpickle>=3.0.0
Requires-Dist: cryptography<47.0,>=42.0.0
Requires-Dist: grpcio-tools==1.75.1
Requires-Dist: grpcio<2.0.0,>=1.75.0
Requires-Dist: httpx>=0.25.0
Requires-Dist: jsonschema-rs<0.30,>=0.20.0
Requires-Dist: langchain-core>=0.3.64
Requires-Dist: langgraph-checkpoint<5,>=3.0.1
Requires-Dist: langgraph-runtime-inmem<0.21.0,>=0.20.0
Requires-Dist: langgraph-sdk>=0.3.0
Requires-Dist: langgraph<2,>=0.4.10
Requires-Dist: langsmith>=0.3.45
Requires-Dist: opentelemetry-api>=1.37.0
Requires-Dist: opentelemetry-exporter-otlp-proto-http>=1.37.0
Requires-Dist: opentelemetry-sdk>=1.37.0
Requires-Dist: orjson>=3.9.7
Requires-Dist: protobuf<7.0.0,>=6.32.1
Requires-Dist: pyjwt>=2.9.0
Requires-Dist: sse-starlette<2.2.0,>=2.1.0
Requires-Dist: starlette>=0.38.6
Requires-Dist: structlog<26,>=24.1.0
Requires-Dist: tenacity>=8.0.0
Requires-Dist: truststore>=0.1
Requires-Dist: uuid-utils>=0.12.0
Requires-Dist: uvicorn>=0.26.0
Requires-Dist: watchfiles>=0.13
